matrix_quant/__init__.py
matrix_quant/matrix.py
matrix_quant-0.0.1.dist-info/LICENSE.txt
matrix_quant-0.0.1.dist-info/METADATA
matrix_quant-0.0.1.dist-info/WHEEL
matrix_quant-0.0.1.dist-info/top_level.txt
matrix_quant-0.0.1.dist-info/RECORD
