Metadata-Version: 2.1
Name: matrix-quant
Version: 0.0.1
Summary: A high performance matrix calculate package
Home-page: https://github.com/lihua179/matrix_quant
Author: Jie
Author-email: UnknowMan@example.com
License: UNKNOWN
Platform: UNKNOWN
Classifier: Programming Language :: Python :: 3
Classifier: License :: OSI Approved :: MIT License
Classifier: Operating System :: OS Independent
Requires-Python: >=3.6
License-File: LICENSE.txt
